setup.py
probab_stats_distributions/Binomialdistribution.py
probab_stats_distributions/Gaussiandistribution.py
probab_stats_distributions/Generaldistribution.py
probab_stats_distributions/__init__.py
probab_stats_distributions.egg-info/PKG-INFO
probab_stats_distributions.egg-info/SOURCES.txt
probab_stats_distributions.egg-info/dependency_links.txt
probab_stats_distributions.egg-info/not-zip-safe
probab_stats_distributions.egg-info/top_level.txt